savory/__init__.py
savory/exceptions.py
savory/savory.py
savory-0.1.4.data/scripts/savory
savory-0.1.4.dist-info/LICENSE
savory-0.1.4.dist-info/METADATA
savory-0.1.4.dist-info/WHEEL
savory-0.1.4.dist-info/top_level.txt
savory-0.1.4.dist-info/zip-safe
savory-0.1.4.dist-info/RECORD
