Metadata-Version: 2.1
Name: savory
Version: 0.1.4
Summary: cli tool to manage saltstack git repositories
Home-page: https://gitlab.com/solvinity/savory
Author: Solvinity
Author-email: shared-services@solvinity.com
License: MIT
Platform: UNKNOWN
License-File: LICENSE
Requires-Dist: gitpython
Requires-Dist: ruamel.yaml
Requires-Dist: click
